{
  "movies": [
    {
      "name": "Inception",
      "trailer": {
        "videoId": "YoHD9XEInc0",
        "embedUrl": "https://www.youtube.com/embed/YoHD9XEInc0"
      }
    },
    {
      "name": "Interstellar",
      "trailer": {
        "videoId": "zSWdZVtXT7E",
        "embedUrl": "https://www.youtube.com/embed/zSWdZVtXT7E"
      }
    },
    {
      "name": "The Dark Knight",
      "trailer": {
        "videoId": "EXeTwQWrcwY",
        "embedUrl": "https://www.youtube.com/embed/EXeTwQWrcwY"
      }
    },
    {
      "name": "Oppenheimer",
      "trailer": {
        "videoId": "bK6ldnjE3Y0",
        "embedUrl": "https://www.youtube.com/embed/bK6ldnjE3Y0"
      }
    }
  ]
}
